Makefile
README.rst
setup.py
democontent/setup-plone.py
democontent/bible/SF_2009-01-20_CHI_CVS_(NEW CHINESE VERSION SIMPLIFIED).xml
democontent/bible/SF_2009-01-20_GER_ALBRECHT1926_(ALBRECHT BIBEL 1926).xml
democontent/bible/SF_2009-01-20_GER_ALMNT_(ALEMANNISCHE BIBEL NT).xml
democontent/bible/SF_2009-01-20_SWA_SWA_(SWAHILI NT).xml
democontent/bible/SF_2009-01-23_HEB_HEBM_(MODERN HEBREW BIBLE).xml
democontent/bible/SF_2010-01-10_CHA_CHAMORRO_(CHAMORRO Y SANTA BIBLIA (1908)).xml
democontent/images/xmldirector.png
democontent/mods/mods-3-0.xsd
democontent/mods/mods-3-1.xsd
democontent/mods/mods-3-2.xsd
democontent/mods/mods-3-3.xsd
democontent/mods/mods-3-4.xsd
democontent/mods/mods-3-5.xsd
democontent/mods/testbibliography.xml
democontent/shakespeare/alls_well_that_ends_well.xml
democontent/shakespeare/antony_cleopatra.xml
democontent/shakespeare/as_you_like_it.xml
democontent/shakespeare/comedy_of_errors.xml
democontent/shakespeare/coriolanus.xml
democontent/shakespeare/cymbeline.xml
democontent/shakespeare/double_falsehood.xml
democontent/shakespeare/edward_iii.xml
democontent/shakespeare/hamlet.xml
democontent/shakespeare/henry_iv_pt1.xml
democontent/shakespeare/henry_iv_pt2.xml
democontent/shakespeare/henry_v.xml
democontent/shakespeare/henry_vi_pt1.xml
democontent/shakespeare/merchant_of_venice.xml
democontent/shakespeare/othello.xml
democontent/shakespeare/passionate_pilgrim.xml
democontent/shakespeare/pericles.xml
democontent/shakespeare/phoenix_and_turtle.xml
democontent/shakespeare/play.xsl
democontent/shakespeare/venus_and_adonis.xml
docs/Makefile
docs/make.bat
docs/source/HISTORY.rst
docs/source/README.rst
docs/source/conf.py
docs/source/content-types.rst
docs/source/index.rst
docs/source/logging.rst
docs/source/testing.rst
docs/source/xslt-registry.rst
docs/source/images/xml-director-logo.jpg
xmldirector/__init__.py
xmldirector.demo.egg-info/PKG-INFO
xmldirector.demo.egg-info/SOURCES.txt
xmldirector.demo.egg-info/dependency_links.txt
xmldirector.demo.egg-info/entry_points.txt
xmldirector.demo.egg-info/namespace_packages.txt
xmldirector.demo.egg-info/not-zip-safe
xmldirector.demo.egg-info/requires.txt
xmldirector.demo.egg-info/top_level.txt
xmldirector/demo/__init__.py
xmldirector/demo/configure.zcml
xmldirector/demo/header.txt
xmldirector/demo/i18n.py
