Metadata-Version: 1.0
Name: xmldirector.demo
Version: 0.1.1
Summary: XML-Director demo package
Home-page: http://pypi.python.org/pypi/xmldirector.demo
Author: Andreas Jung
Author-email: info@zopyx.com
License: GPL
Keywords: xml-director exist-db basex owncloud alfresco existdb Plone XML Python WebDAV
Platform: UNKNOWN
Classifier: Programming Language :: Python
Classifier: Framework :: Plone
Classifier: Framework :: Plone :: 4.3
Classifier: Framework :: Plone :: 5.0
Classifier: Framework :: Zope2
Classifier: Topic :: Software Development :: Libraries :: Python Modules
